numerous/html_report_generator/__init__.py
numerous/html_report_generator/abstract.py
numerous/html_report_generator/block.py
numerous/html_report_generator/caption.py
numerous/html_report_generator/report.py
numerous/html_report_generator/components/__init__.py
numerous/html_report_generator/components/cards.py
numerous/html_report_generator/components/div.py
numerous/html_report_generator/components/figure.py
numerous/html_report_generator/components/section.py
numerous/html_report_generator/components/table.py
numerous/html_report_generator/components/tabs.py
numerous/html_report_generator/components/pandas/__init__.py
numerous/html_report_generator/components/pandas/dataframetable.py
numerous/html_report_generator/components/plotly/__init__.py
numerous/html_report_generator/components/plotly/gofigure.py
numerous/html_report_generator/examples/__init__.py
numerous/html_report_generator/examples/quick_start.py
numerous/html_report_generator/templates/report_template_numerous.html
numerous_html_report_generator-1.7.1.dist-info/LICENSE
numerous_html_report_generator-1.7.1.dist-info/METADATA
numerous_html_report_generator-1.7.1.dist-info/WHEEL
numerous_html_report_generator-1.7.1.dist-info/top_level.txt
numerous_html_report_generator-1.7.1.dist-info/RECORD
