Metadata-Version: 2.1
Name: numerous-html-report-generator
Version: 1.7.1
Summary: Report generator for html reports
Author-email: Tobias Skov Reipuert <report-generator@numerous.com>, Tobias Dokkedal Elmøe <report-generator@numerous.com>, Lasse Nyberg Thomsen <report-generator@numerous.com>, Ósk Björnsdottir <report-generator@numerous.com>
License: O-BSD-3
Project-URL: homepage, https://gitlab.com/numerous/resources/numerous-html-report-generator
Classifier: Programming Language :: Python :: 3
Classifier: License :: OSI Approved :: BSD License
Classifier: Operating System :: OS Independent
Requires-Python: >=3.9
License-File: LICENSE
Requires-Dist: jinja2
Requires-Dist: plotly
Requires-Dist: pytest
Requires-Dist: beautifulsoup4
Requires-Dist: pandas
Requires-Dist: kaleido
